{"meta":{"resultsType":"live","created":1604971816,"wsjTimestamp":"Nov. 9, 2020 at 8:30 p.m. ET"},"data":{"56001":{"unit":"56001","ts":"2020-11-04T05:13:08.203Z","pr":13,"tp":13,"tv":18439,"cand":[{"fname":"Joe","name":"Biden","party":"dem","votes":9091},{"fname":"Donald","name":"Trump","party":"gop","votes":8575,"inc":true,"winner":"X"},{"fname":"Jo","name":"Jorgensen","party":"lib","votes":595},{"fname":"Brock","name":"Pierce","party":"ind","votes":178}],"status":"D"},"56003":{"unit":"56003","ts":"2020-11-04T05:35:22.770Z","pr":13,"tp":13,"tv":5714,"cand":[{"fname":"Donald","name":"Trump","party":"gop","votes":4806,"inc":true,"winner":"X"},{"fname":"Joe","name":"Biden","party":"dem","votes":788},{"fname":"Jo","name":"Jorgensen","party":"lib","votes":74},{"fname":"Brock","name":"Pierce","party":"ind","votes":46}],"status":"R"},"56005":{"unit":"56005","ts":"2020-11-04T06:13:51.330Z","pr":37,"tp":37,"tv":19462,"cand":[{"fname":"Donald","name":"Trump","party":"gop","votes":16973,"inc":true,"winner":"X"},{"fname":"Joe","name":"Biden","party":"dem","votes":1935},{"fname":"Jo","name":"Jorgensen","party":"lib","votes":434},{"fname":"Brock","name":"Pierce","party":"ind","votes":120}],"status":"R"},"56007":{"unit":"56007","ts":"2020-11-04T05:34:20.990Z","pr":19,"tp":19,"tv":6630,"cand":[{"fname":"Donald","name":"Trump","party":"gop","votes":5012,"inc":true,"winner":"X"},{"fname":"Joe","name":"Biden","party":"dem","votes":1427},{"fname":"Jo","name":"Jorgensen","party":"lib","votes":142},{"fname":"Brock","name":"Pierce","party":"ind","votes":49}],"status":"R"},"56009":{"unit":"56009","ts":"2020-11-04T03:43:55.180Z","pr":19,"tp":19,"tv":6941,"cand":[{"fname":"Donald","name":"Trump","party":"gop","votes":5916,"inc":true,"winner":"X"},{"fname":"Joe","name":"Biden","party":"dem","votes":861},{"fname":"Jo","name":"Jorgensen","party":"lib","votes":121},{"fname":"Brock","name":"Pierce","party":"ind","votes":43}],"status":"R"},"56011":{"unit":"56011","ts":"2020-11-04T04:13:19.880Z","pr":17,"tp":17,"tv":4105,"cand":[{"fname":"Donald","name":"Trump","party":"gop","votes":3651,"inc":true,"winner":"X"},{"fname":"Joe","name":"Biden","party":"dem","votes":378},{"fname":"Jo","name":"Jorgensen","party":"lib","votes":57},{"fname":"Brock","name":"Pierce","party":"ind","votes":19}],"status":"R"},"56013":{"unit":"56013","ts":"2020-11-04T04:33:35.740Z","pr":36,"tp":36,"tv":18004,"cand":[{"fname":"Donald","name":"Trump","party":"gop","votes":12007,"inc":true,"winner":"X"},{"fname":"Joe","name":"Biden","party":"dem","votes":5519},{"fname":"Jo","name":"Jorgensen","party":"lib","votes":321},{"fname":"Brock","name":"Pierce","party":"ind","votes":157}],"status":"R"},"56015":{"unit":"56015","ts":"2020-11-04T04:21:23.307Z","pr":25,"tp":25,"tv":6210,"cand":[{"fname":"Donald","name":"Trump","party":"gop","votes":4878,"inc":true,"winner":"X"},{"fname":"Joe","name":"Biden","party":"dem","votes":1203},{"fname":"Jo","name":"Jorgensen","party":"lib","votes":86},{"fname":"Brock","name":"Pierce","party":"ind","votes":43}],"status":"R"},"56017":{"unit":"56017","ts":"2020-11-04T03:08:28.773Z","pr":4,"tp":4,"tv":2566,"cand":[{"fname":"Donald","name":"Trump","party":"gop","votes":1999,"inc":true,"winner":"X"},{"fname":"Joe","name":"Biden","party":"dem","votes":482},{"fname":"Jo","name":"Jorgensen","party":"lib","votes":61},{"fname":"Brock","name":"Pierce","party":"ind","votes":24}],"status":"R"},"56019":{"unit":"56019","ts":"2020-11-04T05:15:09.430Z","pr":16,"tp":16,"tv":4891,"cand":[{"fname":"Donald","name":"Trump","party":"gop","votes":3881,"inc":true,"winner":"X"},{"fname":"Joe","name":"Biden","party":"dem","votes":897},{"fname":"Jo","name":"Jorgensen","party":"lib","votes":86},{"fname":"Brock","name":"Pierce","party":"ind","votes":27}],"status":"R"},"56021":{"unit":"56021","ts":"2020-11-04T05:53:32.647Z","pr":61,"tp":61,"tv":44546,"cand":[{"fname":"Donald","name":"Trump","party":"gop","votes":27814,"inc":true,"winner":"X"},{"fname":"Joe","name":"Biden","party":"dem","votes":15181},{"fname":"Jo","name":"Jorgensen","party":"lib","votes":1060},{"fname":"Brock","name":"Pierce","party":"ind","votes":491}],"status":"R"},"56023":{"unit":"56023","ts":"2020-11-04T05:30:19.257Z","pr":17,"tp":17,"tv":10420,"cand":[{"fname":"Donald","name":"Trump","party":"gop","votes":8673,"inc":true,"winner":"X"},{"fname":"Joe","name":"Biden","party":"dem","votes":1509},{"fname":"Jo","name":"Jorgensen","party":"lib","votes":167},{"fname":"Brock","name":"Pierce","party":"ind","votes":71}],"status":"R"},"56025":{"unit":"56025","ts":"2020-11-04T04:13:19.880Z","pr":50,"tp":50,"tv":34984,"cand":[{"fname":"Donald","name":"Trump","party":"gop","votes":25267,"inc":true,"winner":"X"},{"fname":"Joe","name":"Biden","party":"dem","votes":8528},{"fname":"Jo","name":"Jorgensen","party":"lib","votes":895},{"fname":"Brock","name":"Pierce","party":"ind","votes":294}],"status":"R"},"56027":{"unit":"56027","ts":"2020-11-04T04:34:36.903Z","pr":6,"tp":6,"tv":1305,"cand":[{"fname":"Donald","name":"Trump","party":"gop","votes":1118,"inc":true,"winner":"X"},{"fname":"Joe","name":"Biden","party":"dem","votes":155},{"fname":"Jo","name":"Jorgensen","party":"lib","votes":21},{"fname":"Brock","name":"Pierce","party":"ind","votes":11}],"status":"R"},"56029":{"unit":"56029","ts":"2020-11-04T05:01:02.190Z","pr":31,"tp":31,"tv":16584,"cand":[{"fname":"Donald","name":"Trump","party":"gop","votes":12802,"inc":true,"winner":"X"},{"fname":"Joe","name":"Biden","party":"dem","votes":3404},{"fname":"Jo","name":"Jorgensen","party":"lib","votes":281},{"fname":"Brock","name":"Pierce","party":"ind","votes":97}],"status":"R"},"56031":{"unit":"56031","ts":"2020-11-04T04:03:13.437Z","pr":13,"tp":13,"tv":4902,"cand":[{"fname":"Donald","name":"Trump","party":"gop","votes":3898,"inc":true,"winner":"X"},{"fname":"Joe","name":"Biden","party":"dem","votes":890},{"fname":"Jo","name":"Jorgensen","party":"lib","votes":65},{"fname":"Brock","name":"Pierce","party":"ind","votes":49}],"status":"R"},"56033":{"unit":"56033","ts":"2020-11-04T05:54:33.670Z","pr":33,"tp":33,"tv":16339,"cand":[{"fname":"Donald","name":"Trump","party":"gop","votes":11843,"inc":true,"winner":"X"},{"fname":"Joe","name":"Biden","party":"dem","votes":4043},{"fname":"Jo","name":"Jorgensen","party":"lib","votes":339},{"fname":"Brock","name":"Pierce","party":"ind","votes":114}],"status":"R"},"56035":{"unit":"56035","ts":"2020-11-04T04:49:57.867Z","pr":8,"tp":8,"tv":4947,"cand":[{"fname":"Donald","name":"Trump","party":"gop","votes":3957,"inc":true,"winner":"X"},{"fname":"Joe","name":"Biden","party":"dem","votes":882},{"fname":"Jo","name":"Jorgensen","party":"lib","votes":71},{"fname":"Brock","name":"Pierce","party":"ind","votes":37}],"status":"R"},"56037":{"unit":"56037","ts":"2020-11-04T07:49:25.427Z","pr":37,"tp":37,"tv":16488,"cand":[{"fname":"Donald","name":"Trump","party":"gop","votes":12197,"inc":true,"winner":"X"},{"fname":"Joe","name":"Biden","party":"dem","votes":3822},{"fname":"Jo","name":"Jorgensen","party":"lib","votes":351},{"fname":"Brock","name":"Pierce","party":"ind","votes":118}],"status":"R"},"56039":{"unit":"56039","ts":"2020-11-04T04:36:38.997Z","pr":18,"tp":18,"tv":14533,"cand":[{"fname":"Joe","name":"Biden","party":"dem","votes":9848},{"fname":"Donald","name":"Trump","party":"gop","votes":4341,"inc":true,"winner":"X"},{"fname":"Jo","name":"Jorgensen","party":"lib","votes":255},{"fname":"Brock","name":"Pierce","party":"ind","votes":89}],"status":"D"},"56041":{"unit":"56041","ts":"2020-11-04T04:45:53.783Z","pr":12,"tp":12,"tv":9336,"cand":[{"fname":"Donald","name":"Trump","party":"gop","votes":7494,"inc":true,"winner":"X"},{"fname":"Joe","name":"Biden","party":"dem","votes":1591},{"fname":"Jo","name":"Jorgensen","party":"lib","votes":172},{"fname":"Brock","name":"Pierce","party":"ind","votes":79}],"status":"R"},"56043":{"unit":"56043","ts":"2020-11-04T03:32:45.773Z","pr":5,"tp":5,"tv":3993,"cand":[{"fname":"Donald","name":"Trump","party":"gop","votes":3245,"inc":true,"winner":"X"},{"fname":"Joe","name":"Biden","party":"dem","votes":651},{"fname":"Jo","name":"Jorgensen","party":"lib","votes":65},{"fname":"Brock","name":"Pierce","party":"ind","votes":32}],"status":"R"},"56045":{"unit":"56045","ts":"2020-11-04T03:55:07.143Z","pr":8,"tp":8,"tv":3533,"cand":[{"fname":"Donald","name":"Trump","party":"gop","votes":3107,"inc":true,"winner":"X"},{"fname":"Joe","name":"Biden","party":"dem","votes":360},{"fname":"Jo","name":"Jorgensen","party":"lib","votes":46},{"fname":"Brock","name":"Pierce","party":"ind","votes":20}],"status":"R"},"WY":{"unit":"WY","ts":"2020-11-09T21:52:15.117Z","pr":498,"tp":498,"tv":274872,"cand":[{"fname":"Donald","name":"Trump","party":"gop","votes":193454,"inc":true,"winner":"X","electWon":3},{"fname":"Joe","name":"Biden","party":"dem","votes":73445},{"fname":"Jo","name":"Jorgensen","party":"lib","votes":5765},{"fname":"Brock","name":"Pierce","party":"ind","votes":2208}],"status":"RW","eevp":97}}}